tools_for_distortion/__init__.py
tools_for_distortion/data_parser.py
tools_for_distortion/ranking_generator.py
tools_for_distortion/distortion/__init__.py
tools_for_distortion/distortion/det_distortion.py
tools_for_distortion/distortion/multi_winner_distortion.py
tools_for_distortion/distortion/rand_distortion.py
tools_for_distortion/distortion/social_welfare.py
tools_for_distortion/utils/__init__.py
tools_for_distortion/utils/normalization.py
tools_for_distortion/utils/scoring_rules.py
tools_for_distortion/utils/validators.py
tools_for_distortion/voting_rules/__init__.py
tools_for_distortion/voting_rules/borda.py
tools_for_distortion/voting_rules/boutilier.py
tools_for_distortion/voting_rules/harmonic.py
tools_for_distortion/voting_rules/irv.py
tools_for_distortion/voting_rules/k_approval.py
tools_for_distortion/voting_rules/plurality.py
tools_for_distortion/voting_rules/stv.py
tools_for_distortion-0.6.0.dist-info/LICENSE
tools_for_distortion-0.6.0.dist-info/WHEEL
tools_for_distortion-0.6.0.dist-info/METADATA
tools_for_distortion-0.6.0.dist-info/RECORD
