Metadata-Version: 2.1
Name: tools_for_distortion
Version: 0.6.0
Summary: A brief description of your package
Requires-Python: >=3.6
Requires-Dist: numpy
Requires-Dist: preflibtools
Project-URL: homepage, https://github.com/AshleyDong34/voting_rules_and_distortion
Project-URL: repository, https://github.com/AshleyDong34/voting_rules_and_distortion
